evolib/__init__.py
evolib/api.py
evolib/config/__init__.py
evolib/config/base_component_config.py
evolib/config/component_registry.py
evolib/config/evonet_component_config.py
evolib/config/schema.py
evolib/config/vector_component_config.py
evolib/core/README.md
evolib/core/__init__.py
evolib/core/individual.py
evolib/core/population.py
evolib/envs/gym_wrapper.py
evolib/globals/README.md
evolib/globals/__init__.py
evolib/globals/numeric.py
evolib/initializers/__init__.py
evolib/initializers/evonet_initializers.py
evolib/initializers/net_initializers.py
evolib/initializers/registry.py
evolib/initializers/vector_initializers.py
evolib/interfaces/__init__.py
evolib/interfaces/enum_helpers.py
evolib/interfaces/enums.py
evolib/interfaces/structs.py
evolib/interfaces/types.py
evolib/io/checkpoint.py
evolib/io/serialization.py
evolib/operators/README.md
evolib/operators/__init__.py
evolib/operators/crossover.py
evolib/operators/evonet_structural_mutation.py
evolib/operators/heli.py
evolib/operators/mutation.py
evolib/operators/replacement.py
evolib/operators/reproduction.py
evolib/operators/selection.py
evolib/operators/strategy.py
evolib/registry/__init__.py
evolib/registry/replacement_registry.py
evolib/registry/selection_registry.py
evolib/registry/strategy_registry.py
evolib/representation/__init__.py
evolib/representation/_apply_config_mapping.py
evolib/representation/base.py
evolib/representation/composite.py
evolib/representation/dummy.py
evolib/representation/evo_params.py
evolib/representation/evonet.py
evolib/representation/netvector.py
evolib/representation/vector.py
evolib/utils/README.md
evolib/utils/__init__.py
evolib/utils/benchmarks.py
evolib/utils/config_loader.py
evolib/utils/fitness.py
evolib/utils/heli_experiment_logger.py
evolib/utils/heli_utils.py
evolib/utils/history_logger.py
evolib/utils/lineage_logger.py
evolib/utils/loss_functions.py
evolib/utils/parallel.py
evolib/utils/plotting.py
evolib/utils/random.py
evolib/utils/registry.py
evolib-0.2.0b4.dev4.dist-info/licenses/LICENSE
evolib-0.2.0b4.dev4.dist-info/METADATA
evolib-0.2.0b4.dev4.dist-info/WHEEL
evolib-0.2.0b4.dev4.dist-info/top_level.txt
evolib-0.2.0b4.dev4.dist-info/RECORD
