Metadata-Version: 2.4
Name: evolib
Version: 0.2.0b4.dev4
Summary: A modular framework for evolutionary strategies and neuroevolution.
Author-email: EvoLib <evolib@dismail.de>
License: MIT License
Classifier: Development Status :: 4 - Beta
Classifier: License :: OSI Approved :: MIT License
Classifier: Programming Language :: Python :: 3
Classifier: Programming Language :: Python :: 3.12
Classifier: Topic :: Scientific/Engineering :: Artificial Intelligence
Classifier: Intended Audience :: Education
Requires-Python: >=3.12
License-File: LICENSE
Requires-Dist: numpy<=2.2.6,>=1.24
Requires-Dist: pyyaml>=6.0
Requires-Dist: pandas>=2.3.0
Requires-Dist: pydantic<3.0,>=2.7
Requires-Dist: graphviz>=0.20.1
Requires-Dist: evonet<0.2,>=0.1.0.dev5
Requires-Dist: matplotlib>=3.10
Provides-Extra: dev
Requires-Dist: mypy; extra == "dev"
Requires-Dist: types-PyYAML; extra == "dev"
Requires-Dist: ray; extra == "dev"
Requires-Dist: gymnasium; extra == "dev"
Requires-Dist: imageio; extra == "dev"
Requires-Dist: Box2D; extra == "dev"
Provides-Extra: docs
Requires-Dist: sphinx; extra == "docs"
Requires-Dist: sphinx-rtd-theme; extra == "docs"
Requires-Dist: myst-parser; extra == "docs"
Provides-Extra: test
Requires-Dist: pytest>=8; extra == "test"
Requires-Dist: pytest-cov>=5; extra == "test"
Dynamic: license-file
